oarepo_model_builder_nr/__init__.py
oarepo_model_builder_nr/version.py
oarepo_model_builder_nr/models/__init__.py
oarepo_model_builder_nr/models/datacite_4.5.yaml
oarepo_model_builder_nr/models/datacite_datatypes_4.5.yaml
oarepo_model_builder_nr/models/nr_common_metadata_2.0.yaml
oarepo_model_builder_nr/models/nr_data_2.0.yaml
oarepo_model_builder_nr/models/nr_datatypes_2.0.yaml
oarepo_model_builder_nr/models/nr_documents_2.0.yaml
tests/__init__.py
tests/test_import.py
oarepo_model_builder_nr-2.0.80.dist-info/METADATA
oarepo_model_builder_nr-2.0.80.dist-info/WHEEL
oarepo_model_builder_nr-2.0.80.dist-info/entry_points.txt
oarepo_model_builder_nr-2.0.80.dist-info/top_level.txt
oarepo_model_builder_nr-2.0.80.dist-info/RECORD
