Metadata-Version: 2.4
Name: oarepo-model-builder-nr
Version: 2.0.80
Summary: "A model builder plugin with Czech National Repository compatible metadata schema"
Home-page: https://github.com/Narodni-repozitar/oarepo-model-builder-nr
Author: Miroslav Simek
Author-email: simek.miroslav@techlib.cz
License: MIT
Keywords: invenio Czech NR model builder
Platform: any
Classifier: Development Status :: 3 - Alpha
Requires-Python: >=3.9
Requires-Dist: oarepo-model-builder>=3.0.0
Requires-Dist: oarepo-model-builder-vocabularies>=1.0.0
Requires-Dist: oarepo-model-builder-ui
Requires-Dist: oarepo-model-builder-multilingual
Provides-Extra: tests
Requires-Dist: pytest; extra == "tests"
